rmon/__init__.py
rmon/common.py
rmon/loggers.py
rmon/models.py
rmon/plots.py
rmon/py.typed
rmon/resource_monitor.py
rmon/resource_stat_aggregator.py
rmon/resource_stat_collector.py
rmon/resource_stat_store.py
rmon/version.py
rmon/cli/__init__.py
rmon/cli/collect.py
rmon/cli/plot.py
rmon/cli/rmon.py
rmon/timing/README.md
rmon/timing/__init__.py
rmon/timing/timer_stats.py
rmon/timing/timer_utils.py
rmon/utils/__init__.py
rmon/utils/sql.py
rmon-0.5.0.dist-info/METADATA
rmon-0.5.0.dist-info/WHEEL
rmon-0.5.0.dist-info/entry_points.txt
rmon-0.5.0.dist-info/licenses/LICENSE
rmon-0.5.0.dist-info/RECORD
