Metadata-Version: 2.4
Name: rmon
Version: 0.5.0
Author-email: Daniel Thom <daniel.thom@nrel.gov>
License: BSD 3-Clause License
License-File: LICENSE
Classifier: Development Status :: 4 - Beta
Classifier: License :: OSI Approved :: BSD License
Classifier: Natural Language :: English
Classifier: Programming Language :: Python :: 3.10
Requires-Python: >=3.11
Requires-Dist: click<9,>=8.2
Requires-Dist: loguru
Requires-Dist: plotly<6,>=5.19
Requires-Dist: psutil<8,>=7.1
Requires-Dist: pydantic<3,>=2.1
Requires-Dist: python-daemon
Requires-Dist: rich-click
Provides-Extra: dev
Requires-Dist: mypy; extra == 'dev'
Requires-Dist: pre-commit; extra == 'dev'
Requires-Dist: pytest; extra == 'dev'
Requires-Dist: pytest-cov; extra == 'dev'
Requires-Dist: ruff; extra == 'dev'
Requires-Dist: types-psutil; extra == 'dev'
Requires-Dist: types-setuptools; extra == 'dev'
